gist_dl/__init__.py
gist_dl/gist/__init__.py
gist_dl/gist/gist.py
gist_dl/github/__init__.py
gist_dl/github/gh.py
gist_dl-0.1.1.dist-info/METADATA
gist_dl-0.1.1.dist-info/WHEEL
gist_dl-0.1.1.dist-info/RECORD
